ovos_microphone_plugin_sounddevice/__init__.py
ovos_microphone_plugin_sounddevice/version.py
ovos_microphone_plugin_sounddevice-0.0.2.dist-info/licenses/LICENSE
ovos_microphone_plugin_sounddevice-0.0.2.dist-info/METADATA
ovos_microphone_plugin_sounddevice-0.0.2.dist-info/WHEEL
ovos_microphone_plugin_sounddevice-0.0.2.dist-info/entry_points.txt
ovos_microphone_plugin_sounddevice-0.0.2.dist-info/top_level.txt
ovos_microphone_plugin_sounddevice-0.0.2.dist-info/zip-safe
ovos_microphone_plugin_sounddevice-0.0.2.dist-info/RECORD
