Metadata-Version: 2.4
Name: ovos_microphone_plugin_sounddevice
Version: 0.0.2
Summary: A sounddevice microphone implementation for OVOS
Home-page: https://github.com/OpenVoiceOS/ovos-microphone-plugin-sounddevice
Author: Gaëtan Trellu (goldyfruit)
Author-email: gaetan.trellu@gmail.com
License: Apache-2.0
Keywords: ovos plugin listener microphone sounddevice
Classifier: Development Status :: 3 - Alpha
Classifier: Intended Audience :: Developers
Classifier: Topic :: Text Processing :: Linguistic
Classifier: License :: OSI Approved :: Apache Software License
Classifier: Programming Language :: Python :: 2
Classifier: Programming Language :: Python :: 2.7
Classifier: Programming Language :: Python :: 3
Classifier: Programming Language :: Python :: 3.0
Classifier: Programming Language :: Python :: 3.1
Classifier: Programming Language :: Python :: 3.2
Classifier: Programming Language :: Python :: 3.3
Classifier: Programming Language :: Python :: 3.4
Classifier: Programming Language :: Python :: 3.5
Classifier: Programming Language :: Python :: 3.6
License-File: LICENSE
Requires-Dist: ovos-plugin-manager<3.0.0,>=0.0.23
Requires-Dist: SpeechRecognition>=3.8.1
Requires-Dist: sounddevice
Dynamic: author
Dynamic: author-email
Dynamic: classifier
Dynamic: home-page
Dynamic: keywords
Dynamic: license
Dynamic: license-file
Dynamic: requires-dist
Dynamic: summary
